.gitignore
FAQ.md
LICENSE.txt
NOTICE.md
README.md
meta.json
requirements.txt
setup.py
volcengine_bioos_test_python.egg-info/PKG-INFO
volcengine_bioos_test_python.egg-info/SOURCES.txt
volcengine_bioos_test_python.egg-info/dependency_links.txt
volcengine_bioos_test_python.egg-info/requires.txt
volcengine_bioos_test_python.egg-info/top_level.txt
volcenginesdkalb/__init__.py
volcenginesdkalb/api/__init__.py
volcenginesdkalb/api/alb_api.py
volcenginesdkalb/models/__init__.py
volcenginesdkalb/models/access_log_for_describe_load_balancer_attributes_output.py
volcenginesdkalb/models/acl_entry_for_add_acl_entries_input.py
volcenginesdkalb/models/acl_entry_for_describe_acl_attributes_output.py
volcenginesdkalb/models/acl_for_describe_acls_output.py
volcenginesdkalb/models/add_acl_entries_request.py
volcenginesdkalb/models/add_acl_entries_response.py
volcenginesdkalb/models/add_server_group_backend_servers_request.py
volcenginesdkalb/models/add_server_group_backend_servers_response.py
volcenginesdkalb/models/ca_certificate_for_describe_ca_certificates_output.py
volcenginesdkalb/models/certificate_for_describe_all_certificates_output.py
volcenginesdkalb/models/certificate_for_describe_certificates_output.py
volcenginesdkalb/models/create_acl_request.py
volcenginesdkalb/models/create_acl_response.py
volcenginesdkalb/models/create_customized_cfg_request.py
volcenginesdkalb/models/create_customized_cfg_response.py
volcenginesdkalb/models/create_health_check_templates_request.py
volcenginesdkalb/models/create_health_check_templates_response.py
volcenginesdkalb/models/create_listener_request.py
volcenginesdkalb/models/create_listener_response.py
volcenginesdkalb/models/create_load_balancer_request.py
volcenginesdkalb/models/create_load_balancer_response.py
volcenginesdkalb/models/create_rules_request.py
volcenginesdkalb/models/create_rules_response.py
volcenginesdkalb/models/create_server_group_request.py
volcenginesdkalb/models/create_server_group_response.py
volcenginesdkalb/models/customized_cfg_for_describe_customized_cfgs_output.py
volcenginesdkalb/models/delete_acl_request.py
volcenginesdkalb/models/delete_acl_response.py
volcenginesdkalb/models/delete_ca_certificate_request.py
