Metadata-Version: 2.1
Name: volcengine-bioos-test-python
Version: 1.0.42
Summary: Volcengine Bio2s SDK for Python
License: Apache License 2.0
Platform: any
License-File: LICENSE.txt
License-File: NOTICE.md
